pydantic_tensor/__about__.py
pydantic_tensor/__init__.py
pydantic_tensor/delegate.py
pydantic_tensor/interface.py
pydantic_tensor/tensor.py
pydantic_tensor/types.py
pydantic_tensor/backend/jax.py
pydantic_tensor/backend/numpy.py
pydantic_tensor/backend/tensorflow.py
pydantic_tensor/backend/torch.py
pydantic_tensor/pydantic/dtype.py
pydantic_tensor/pydantic/shape.py
pydantic_tensor/utils/base64.py
pydantic_tensor/utils/convert.py
pydantic_tensor/utils/dedupe.py
pydantic_tensor/utils/type.py
pydantic_tensor/utils/type_annotation.py
pydantic_tensor-0.2.0.dist-info/METADATA
pydantic_tensor-0.2.0.dist-info/WHEEL
pydantic_tensor-0.2.0.dist-info/licenses/LICENSE.txt
pydantic_tensor-0.2.0.dist-info/RECORD
