Metadata-Version: 2.3
Name: pydantic-tensor
Version: 0.2.0
Summary: Pydantic support for parsing, validation, and serialization of tensors
Project-URL: Documentation, https://github.com/dominik-schwabe/pydantic-tensor#readme
Project-URL: Issues, https://github.com/dominik-schwabe/pydantic-tensor/issues
Project-URL: Source, https://github.com/dominik-schwabe/pydantic-tensor
Author-email: Dominik Schwabe <schwabedominik@gmail.com>
License-Expression: MIT
License-File: LICENSE.txt
Classifier: Development Status :: 4 - Beta
Classifier: Programming Language :: Python
Classifier: Programming Language :: Python :: 3.9
Classifier: Programming Language :: Python :: 3.10
Classifier: Programming Language :: Python :: 3.11
Classifier: Programming Language :: Python :: 3.12
Classifier: Programming Language :: Python :: Implementation :: CPython
Classifier: Programming Language :: Python :: Implementation :: PyPy
Requires-Python: >=3.9
Requires-Dist: numpy
Requires-Dist: pydantic>=2.6
